odoo/addons/report_qweb_pdf_watermark/README.rst
odoo/addons/report_qweb_pdf_watermark/__init__.py
odoo/addons/report_qweb_pdf_watermark/__manifest__.py
odoo/addons/report_qweb_pdf_watermark/demo/report.xml
odoo/addons/report_qweb_pdf_watermark/i18n/ca.po
odoo/addons/report_qweb_pdf_watermark/i18n/da.po
odoo/addons/report_qweb_pdf_watermark/i18n/de.po
odoo/addons/report_qweb_pdf_watermark/i18n/el_GR.po
odoo/addons/report_qweb_pdf_watermark/i18n/es.po
odoo/addons/report_qweb_pdf_watermark/i18n/es_CO.po
odoo/addons/report_qweb_pdf_watermark/i18n/fr.po
odoo/addons/report_qweb_pdf_watermark/i18n/gl.po
odoo/addons/report_qweb_pdf_watermark/i18n/hr.po
odoo/addons/report_qweb_pdf_watermark/i18n/hr_HR.po
odoo/addons/report_qweb_pdf_watermark/i18n/it.po
odoo/addons/report_qweb_pdf_watermark/i18n/nb_NO.po
odoo/addons/report_qweb_pdf_watermark/i18n/nl.po
odoo/addons/report_qweb_pdf_watermark/i18n/nl_NL.po
odoo/addons/report_qweb_pdf_watermark/i18n/pl.po
odoo/addons/report_qweb_pdf_watermark/i18n/pt.po
odoo/addons/report_qweb_pdf_watermark/i18n/pt_BR.po
odoo/addons/report_qweb_pdf_watermark/i18n/pt_PT.po
odoo/addons/report_qweb_pdf_watermark/i18n/report_qweb_pdf_watermark.pot
odoo/addons/report_qweb_pdf_watermark/i18n/sl.po
odoo/addons/report_qweb_pdf_watermark/i18n/tr.po
odoo/addons/report_qweb_pdf_watermark/i18n/tr_TR.po
odoo/addons/report_qweb_pdf_watermark/models/__init__.py
odoo/addons/report_qweb_pdf_watermark/models/report.py
odoo/addons/report_qweb_pdf_watermark/models/res_company.py
odoo/addons/report_qweb_pdf_watermark/readme/CONTRIBUTORS.md
odoo/addons/report_qweb_pdf_watermark/readme/DESCRIPTION.md
odoo/addons/report_qweb_pdf_watermark/readme/HISTORY.md
odoo/addons/report_qweb_pdf_watermark/readme/INSTALL.md
odoo/addons/report_qweb_pdf_watermark/readme/ROADMAP.md
odoo/addons/report_qweb_pdf_watermark/readme/USAGE.md
odoo/addons/report_qweb_pdf_watermark/static/description/icon.png
odoo/addons/report_qweb_pdf_watermark/static/description/index.html
odoo_addon_report_qweb_pdf_watermark-18.0.1.0.1.2.dist-info/METADATA
odoo_addon_report_qweb_pdf_watermark-18.0.1.0.1.2.dist-info/WHEEL
odoo_addon_report_qweb_pdf_watermark-18.0.1.0.1.2.dist-info/top_level.txt
odoo_addon_report_qweb_pdf_watermark-18.0.1.0.1.2.dist-info/RECORD
