Metadata-Version: 2.1
Name: odoo-addon-report_qweb_pdf_watermark
Version: 18.0.1.0.1.2
Requires-Python: >=3.10
Requires-Dist: odoo==18.0.*
Summary: Add watermarks to your QWEB PDF reports
Home-page: https://github.com/OCA/reporting-engine
License: AGPL-3
Author: Therp BV, Odoo Community Association (OCA)
Author-email: support@odoo-community.org
Classifier: Programming Language :: Python
Classifier: Framework :: Odoo
Classifier: Framework :: Odoo :: 18.0
Classifier: License :: OSI Approved :: GNU Affero General Public License v3
Classifier: Development Status :: 5 - Production/Stable
